data_quality/__init__.py
data_quality/main.py
data_quality/config/__init__.py
data_quality/config/columns_config.yaml
data_quality/config/model_config.yaml
data_quality/core/__init__.py
data_quality/core/answer_processor.py
data_quality/core/answer_relevance_processor.py
data_quality/core/base.py
data_quality/core/context_processor.py
data_quality/core/context_relevance_processor.py
data_quality/core/groundedness_processor.py
data_quality/core/processor_factory.py
data_quality/core/reward_processor.py
data_quality/data/__init__.py
data_quality/data/base.py
data_quality/data/csv_handler.py
data_quality/data/data_factory.py
data_quality/data/excel_handler.py
data_quality/data/json_handler.py
data_quality/data/jsonl_handler.py
data_quality/data/txt_handler.py
data_quality/evaluators/AnswerRelevance.py
data_quality/evaluators/ContextRelevance.py
data_quality/evaluators/__init__.py
data_quality/evaluators/answer.py
data_quality/evaluators/base.py
data_quality/evaluators/context.py
data_quality/evaluators/groundedness.py
data_quality/evaluators/reward.py
data_quality/models/__init__.py
data_quality/models/base.py
data_quality/models/qwen2_72b_model.py
data_quality/models/qwen3_32b_model.py
data_quality/models/qwen_model.py
data_quality/prompt/__init__.py
data_quality/prompt/answer_prompt.yaml
data_quality/prompt/answer_relevance_prompt.yaml
data_quality/prompt/context_prompt.yaml
data_quality/prompt/context_relevance_prompt.yaml
data_quality/prompt/groundedness_prompt.yaml
data_quality/prompt/reward_prompt.yaml
data_quality/utils/__init__.py
data_quality/utils/calibrator.py
data_quality/utils/extra_yaml.py
data_quality/utils/logger.py
eazy_data_quality-0.1.1.dist-info/METADATA
eazy_data_quality-0.1.1.dist-info/WHEEL
eazy_data_quality-0.1.1.dist-info/entry_points.txt
eazy_data_quality-0.1.1.dist-info/top_level.txt
eazy_data_quality-0.1.1.dist-info/RECORD
