Metadata-Version: 2.4
Name: eazy-data-quality
Version: 0.1.1
Summary: A data quality evaluation toolkit for Q&A, context, and relevance scoring
Author-email: yang <1325320950@qq.com>
License: MIT
Keywords: data-quality,evaluation,nlp,llm
Classifier: Programming Language :: Python :: 3
Classifier: Programming Language :: Python :: 3.11
Classifier: License :: OSI Approved :: MIT License
Classifier: Operating System :: OS Independent
Requires-Python: >=3.8
Requires-Dist: numpy<2.4,>=1.26
Requires-Dist: openpyxl<3.2,>=3.1.3
Requires-Dist: pandas<2.3,>=2.0.3
Requires-Dist: pipreqs<0.6,>=0.5
Requires-Dist: pyyaml<7.0,>=6.0.2
Requires-Dist: requests<3.0,>=2.32.0
Requires-Dist: urllib3<3.0,>=2.6.0
